memcachier_django/__init__.py
memcachier_django/ascii.py
memcachier_django/client.py
memcachier_django_ascii-1.0.0.dev1.dist-info/DESCRIPTION.rst
memcachier_django_ascii-1.0.0.dev1.dist-info/METADATA
memcachier_django_ascii-1.0.0.dev1.dist-info/metadata.json
memcachier_django_ascii-1.0.0.dev1.dist-info/RECORD
memcachier_django_ascii-1.0.0.dev1.dist-info/top_level.txt
memcachier_django_ascii-1.0.0.dev1.dist-info/WHEEL
