Metadata-Version: 2.0
Name: memcachier-django-ascii
Version: 1.0.0.dev1
Summary: Django cache backend supporting MemCachier service
Home-page: https://github.com/memcachier/django-ascii
Author: MemCachier
Author-email: support@memcachier.com
License: BSD
Platform: UNKNOWN
Classifier: Development Status :: 4 - Beta
Classifier: Environment :: Web Environment
Classifier: Intended Audience :: Developers
Classifier: Framework :: Django
Classifier: Operating System :: OS Independent
Classifier: Programming Language :: Python
Classifier: License :: OSI Approved :: Apache Software License
Classifier: Topic :: Database
Classifier: Topic :: Caching
Requires-Dist: pymemcache
